README.rst
setup.py
external/__init__.py
external/absl_py/__init__.py
external/absl_py/absl/__init__.py
external/absl_py/absl/flags/__init__.py
external/absl_py/absl/flags/_argument_parser.py
external/absl_py/absl/flags/_defines.py
external/absl_py/absl/flags/_exceptions.py
external/absl_py/absl/flags/_flag.py
external/absl_py/absl/flags/_flagvalues.py
external/absl_py/absl/flags/_helpers.py
external/absl_py/absl/flags/_validators.py
external/astor_archive/__init__.py
external/astor_archive/astor/__init__.py
external/astor_archive/astor/code_gen.py
external/astor_archive/astor/codegen.py
external/astor_archive/astor/file_util.py
external/astor_archive/astor/node_util.py
external/astor_archive/astor/op_util.py
external/astor_archive/astor/rtrip.py
external/astor_archive/astor/source_repr.py
external/astor_archive/astor/string_repr.py
external/astor_archive/astor/tree_walk.py
external/gast_archive/__init__.py
external/gast_archive/gast/__init__.py
external/gast_archive/gast/ast2.py
external/gast_archive/gast/ast3.py
external/gast_archive/gast/astn.py
external/gast_archive/gast/gast.py
external/org_python_pypi_backports_weakref/__init__.py
external/org_python_pypi_backports_weakref/backports/__init__.py
external/org_python_pypi_backports_weakref/backports/weakref.py
external/protobuf_archive/__init__.py
external/protobuf_archive/python/__init__.py
external/protobuf_archive/python/compatibility_tests/__init__.py
external/protobuf_archive/python/google/__init__.py
external/protobuf_archive/python/google/protobuf/__init__.py
external/protobuf_archive/python/google/protobuf/any_pb2.py
external/protobuf_archive/python/google/protobuf/api_pb2.py
external/protobuf_archive/python/google/protobuf/descriptor.py
external/protobuf_archive/python/google/protobuf/descriptor_database.py
external/protobuf_archive/python/google/protobuf/descriptor_pb2.py
external/protobuf_archive/python/google/protobuf/descriptor_pool.py
external/protobuf_archive/python/google/protobuf/duration_pb2.py
tensorflow_gpu_macosx.egg-info/.DS_Store
tensorflow_gpu_macosx.egg-info/DESCRIPTION.rst
tensorflow_gpu_macosx.egg-info/METADATA
tensorflow_gpu_macosx.egg-info/PKG-INFO
tensorflow_gpu_macosx.egg-info/RECORD
tensorflow_gpu_macosx.egg-info/SOURCES.txt
tensorflow_gpu_macosx.egg-info/WHEEL
tensorflow_gpu_macosx.egg-info/dependency_links.txt
tensorflow_gpu_macosx.egg-info/entry_points.txt
tensorflow_gpu_macosx.egg-info/metadata.json
tensorflow_gpu_macosx.egg-info/not-zip-safe
tensorflow_gpu_macosx.egg-info/requires.txt
tensorflow_gpu_macosx.egg-info/top_level.txt