Metadata-Version: 1.1
Name: tensorflow-gpu-macosx
Version: 1.8.1
Summary: Unoffcial NVIDIA CUDA GPU support version of Google Tensorflow for MAC OSX 10.13. For more info, please check out my github page. I highly recommend you directly download and install it from my github's release. If you insist on compiling it, you'd do it on a shell to debug.
Home-page: https://github.com/zylo117/tensorflow-gpu-macosx
Author: Carl Cheung
Author-email: zylo117@hotmail.com
License: Apache 2.0
Keywords: tensorflow tensor machine learning
Platform: UNKNOWN
Classifier: Development Status :: 4 - Beta
Classifier: Intended Audience :: Developers
Classifier: Intended Audience :: Education
Classifier: Intended Audience :: Science/Research
Classifier: License :: OSI Approved :: Apache Software License
Classifier: Programming Language :: Python :: 2
Classifier: Programming Language :: Python :: 2.7
Classifier: Programming Language :: Python :: 3
Classifier: Programming Language :: Python :: 3.4
Classifier: Programming Language :: Python :: 3.5
Classifier: Programming Language :: Python :: 3.6
Classifier: Topic :: Scientific/Engineering
Classifier: Topic :: Scientific/Engineering :: Mathematics
Classifier: Topic :: Scientific/Engineering :: Artificial Intelligence
Classifier: Topic :: Software Development
Classifier: Topic :: Software Development :: Libraries
Classifier: Topic :: Software Development :: Libraries :: Python Modules
